sendwhappmsg/__init__.py
sendwhappmsg-0.0.2.dist-info/LICENSE.txt
sendwhappmsg-0.0.2.dist-info/METADATA
sendwhappmsg-0.0.2.dist-info/WHEEL
sendwhappmsg-0.0.2.dist-info/top_level.txt
sendwhappmsg-0.0.2.dist-info/RECORD
