Metadata-Version: 2.1
Name: sendwhappmsg
Version: 0.0.2
Summary: This module will send any whatsapp message to any mobile no.
Home-page: https://github.com/Ankitsinghprograms/sendwhatsappmsg
Author: Ankit Singh
Author-email: ankitsingh300307@gmail.com.com
License: UNKNOWN
Platform: UNKNOWN
Classifier: Programming Language :: Python :: 3
Classifier: License :: OSI Approved :: MIT License
Classifier: Operating System :: OS Independent
Requires-Python: >=3.6
